constructor_groups/__init__.py
constructor_groups/client.py
constructor_groups/attendee/__init__.py
constructor_groups/attendee/client.py
constructor_groups/report/__init__.py
constructor_groups/report/client.py
constructor_groups/session/__init__.py
constructor_groups/session/client.py
constructor_groups/user/__init__.py
constructor_groups/user/client.py
constructor_groups-0.2.5.dist-info/METADATA
constructor_groups-0.2.5.dist-info/WHEEL
constructor_groups-0.2.5.dist-info/top_level.txt
constructor_groups-0.2.5.dist-info/RECORD
